expedantic/__init__.py
expedantic/config_base.py
expedantic/utils.py
expedantic/yaml_utils.py
expedantic/constraints/conditional.py
expedantic/constraints/numerics.py
expedantic/printers/__init__.py
expedantic/printers/diff.py
expedantic/printers/help.py
expedantic/printers/utils.py
expedantic/printers/validation.py
ccorp/ruamel/yaml/include/__init__.py
expedantic-0.2.3.dist-info/METADATA
expedantic-0.2.3.dist-info/WHEEL
expedantic-0.2.3.dist-info/licenses/LICENSE
expedantic-0.2.3.dist-info/RECORD
