Metadata-Version: 2.4
Name: expedantic
Version: 0.2.3
Project-URL: Homepage, https://github.com/rnilva/expedantic
Author-email: rnilva <rnilva849@gmail.com>
License-Expression: MIT
License-File: LICENSE
Requires-Python: >=3.10
Requires-Dist: pydantic-yaml>=1.3.0
Requires-Dist: pydantic>=2.10.5
Requires-Dist: rich>=13.7.1
Requires-Dist: typed-argument-parser
